activitypubdantic/__init__.py
activitypubdantic/get_class.py
activitypubdantic/get_model.py
activitypubdantic/models/__init__.py
activitypubdantic/models/activity.py
activitypubdantic/models/actor.py
activitypubdantic/models/core.py
activitypubdantic/models/link.py
activitypubdantic/models/object.py
activitypubdantic/models/_utils/__init__.py
activitypubdantic/models/_utils/language_types.py
activitypubdantic/models/_utils/mime_types.py
activitypubdantic-0.0.3.dist-info/METADATA
activitypubdantic-0.0.3.dist-info/WHEEL
activitypubdantic-0.0.3.dist-info/licenses/LICENSE
activitypubdantic-0.0.3.dist-info/RECORD
