Metadata-Version: 2.1
Name: activitypubdantic
Version: 0.0.3
Summary: Pydantic Models for ActivityPub with Classes for Enabling Interactions
Project-URL: Homepage, https://github.com/joewlos/activitypubdantic
Project-URL: Documentation, https://www.joewlos.com/activitypubdantic/
Author-email: Joe Wlos <joewlos17@gmail.com>
License-File: LICENSE
Classifier: License :: OSI Approved :: MIT License
Classifier: Operating System :: OS Independent
Classifier: Programming Language :: Python :: 3
Requires-Python: >=3.7
Requires-Dist: pydantic==2.0.3
